vl/__init__.py
vl/cli.py
vl-0.3.4.dist-info/DESCRIPTION.rst
vl-0.3.4.dist-info/METADATA
vl-0.3.4.dist-info/RECORD
vl-0.3.4.dist-info/WHEEL
vl-0.3.4.dist-info/entry_points.txt
vl-0.3.4.dist-info/metadata.json
vl-0.3.4.dist-info/top_level.txt
