Metadata-Version: 2.0
Name: vl
Version: 0.3.4
Summary: A URL link checker CLI command for text files.
Home-page: https://github.com/ellisonleao/vl
Author: Ellison Leão
Author-email: ellisonleao@gmail.com
License: MIT
Platform: a
Platform: n
Platform: y
Classifier: Development Status :: 4 - Beta
Classifier: Environment :: Console
Classifier: Intended Audience :: Developers
Classifier: License :: OSI Approved :: BSD License
Classifier: Operating System :: POSIX
Classifier: Operating System :: MacOS
Classifier: Operating System :: Unix
Classifier: Operating System :: Microsoft :: Windows
Classifier: Programming Language :: Python
Classifier: Programming Language :: Python :: 2
Classifier: Programming Language :: Python :: 3
Classifier: Topic :: Software Development :: Libraries :: Python Modules
Requires-Dist: click (==6.7)
Requires-Dist: grequests (==0.3.0)
Requires-Dist: six (==1.10.0)
